pytabchen/__init__.py
pytabchen/utils/__init__.py
pytabchen/utils/io_utils.py
pytabchen-0.0.1.2.dist-info/LICENSE
pytabchen-0.0.1.2.dist-info/METADATA
pytabchen-0.0.1.2.dist-info/WHEEL
pytabchen-0.0.1.2.dist-info/top_level.txt
pytabchen-0.0.1.2.dist-info/RECORD
