Metadata-Version: 2.1
Name: pytabchen
Version: 0.0.1.2
Summary: Finder papers
Home-page: https://github.com/meta-tabchen/py-tabchen
Author: TabChen
Author-email: 2808581543@qq.com
License: UNKNOWN
Project-URL: Bug Tracker, https://github.com/meta-tabchen/py-tabchen/issues
Platform: UNKNOWN
Classifier: Programming Language :: Python :: 3
Classifier: License :: OSI Approved :: MIT License
Classifier: Operating System :: OS Independent
Requires-Python: >=3.1
License-File: LICENSE
Requires-Dist: numpy
Requires-Dist: pandas
Requires-Dist: tqdm
